{"assignmentId":"projekt","jagrVersion":"0.7.0","sourceSets":[{"name":"grader","files":{}},{"name":"main","files":{"java":["projekt/Main.java"]}},{"name":"test","files":{}}],"dependencyConfigurations":{"graderImplementation":["org.tudalgo:algoutils-tutor:0.4.0","org.sourcegrade:jagr-launcher:0.7.0"],"implementation":["org.jetbrains:annotations:23.0.0","org.tudalgo:algoutils-student:0.6.0","com.formdev:flatlaf:2.0.1","FOP-2223-Projekt-Student:application:unspecified"],"runtimeOnly":["FOP-2223-Projekt-Student:infrastructure:unspecified"],"testImplementation":["org.junit.jupiter:junit-jupiter:5.9.1"]},"repositoryConfigurations":[{"name":"MavenLocal","url":"file:/C:/Users/jo_dr/.m2/repository/"},{"name":"maven","url":"https://s01.oss.sonatype.org/content/repositories/snapshots"},{"name":"MavenRepo","url":"https://repo.maven.apache.org/maven2/"}],"name":"FOP-2223-Projekt-Public","rubricProviderName":"projekt.Projekt_RubricProvider"}